pyopenair/__init__.py
pyopenair/factory.py
pyopenair/helper.py
pyopenair/main.py
pyopenair/templates/single_element.txt
pyopenair-1.2.1.dist-info/LICENSE
pyopenair-1.2.1.dist-info/METADATA
pyopenair-1.2.1.dist-info/WHEEL
pyopenair-1.2.1.dist-info/entry_points.txt
pyopenair-1.2.1.dist-info/RECORD
