Metadata-Version: 2.1
Name: pyopenair
Version: 1.2.1
Summary: A simple python package to convert geo data to OpenAir format
Home-page: https://github.com/lpoaura/pyopenair
License: AGPL-3.0-or-later
Keywords: openair,paragliding,wkt2openair,geo2openair,airspace
Author: lpofredc
Author-email: frederic.cloitre@lpo.fr
Requires-Python: >=3.8,<4.0.0
Classifier: License :: OSI Approved :: GNU Affero General Public License v3 or later (AGPLv3+)
Classifier: License :: OSI Approved :: GNU General Public License v3 (GPLv3)
Classifier: Operating System :: OS Independent
Classifier: Programming Language :: Python :: 3
Classifier: Programming Language :: Python :: 3.8
Classifier: Programming Language :: Python :: 3.9
Classifier: Programming Language :: Python :: 3.10
Classifier: Programming Language :: Python :: 3.11
Requires-Dist: Shapely (>=2.0.0,<3.0.0)
Project-URL: Bug Tracker, https://github.com/lpoaura/pyopenair/issues
Project-URL: Documentation, https://pyopenair.readthedocs.io
Project-URL: Repository, https://github.com/lpoaura/pyopenair
